Metadata-Version: 2.1
Name: ScorpioConversionRuntime
Version: 1.0.1
Summary: https://github.com/qingfeng346/ScorpioConversion python基础运行库
Home-page: https://github.com/qingfeng346/ScorpioConversion
Author: while
Author-email: qingfeng346@outlook.com
License: UNKNOWN
Platform: UNKNOWN
